Metadata-Version: 2.1
Name: stat-basic-dist
Version: 0.1
Summary: Gaussian and Bionomial distributions
Home-page: https://github.com/sam-karis/stat-dist
Author: Sammy Kariuki
Author-email: samkaris75@gmail.com
License: UNKNOWN
Platform: UNKNOWN
